pymetrics_assessment_api_client/LICENSE.txt
pymetrics_assessment_api_client/__init__.py
pymetrics_assessment_api_client/api/__init__.py
pymetrics_assessment_api_client/api/default/__init__.py
pymetrics_assessment_api_client/api/default/mercury_create_order.py
pymetrics_assessment_api_client/api/default/mercury_get_config.py
pymetrics_assessment_api_client/api/default/mercury_list_orders.py
pymetrics_assessment_api_client/api/default/mercury_o_auth.py
pymetrics_assessment_api_client/api/default/mercury_retrieve_order.py
pymetrics_assessment_api_client/client.py
pymetrics_assessment_api_client/examples/constants.py
pymetrics_assessment_api_client/examples/example_mercury_create_and_retrieve_order.py
pymetrics_assessment_api_client/examples/example_mercury_get_config.py
pymetrics_assessment_api_client/examples/example_mercury_get_oauth.py
pymetrics_assessment_api_client/examples/example_mercury_list_orders.py
pymetrics_assessment_api_client/examples/example_mercury_retrieve_order.py
pymetrics_assessment_api_client/models/__init__.py
pymetrics_assessment_api_client/models/assessment_type.py
pymetrics_assessment_api_client/models/ats_type.py
pymetrics_assessment_api_client/models/mercury_assessment.py
pymetrics_assessment_api_client/models/mercury_assessment_order.py
pymetrics_assessment_api_client/models/mercury_assessment_order_metadata.py
pymetrics_assessment_api_client/models/mercury_candidate.py
pymetrics_assessment_api_client/models/mercury_configuration.py
pymetrics_assessment_api_client/models/mercury_error_response.py
pymetrics_assessment_api_client/models/mercury_list_orders_request.py
pymetrics_assessment_api_client/models/mercury_list_orders_response.py
pymetrics_assessment_api_client/models/mercury_order_create_response.py
pymetrics_assessment_api_client/models/mercury_order_request.py
pymetrics_assessment_api_client/models/mercury_order_request_metadata.py
pymetrics_assessment_api_client/models/mercury_report.py
pymetrics_assessment_api_client-1.0.1.dist-info/WHEEL
pymetrics_assessment_api_client-1.0.1.dist-info/METADATA
pymetrics_assessment_api_client-1.0.1.dist-info/RECORD
