Metadata-Version: 2.1
Name: pymetrics-assessment-api-client
Version: 1.0.1
Summary: A client library for accessing pymetrics Assessment API
Home-page: https://github.com/pymetrics/pymetrics_assessment_api_client
License: MIT
Author: Michelle Tsai
Author-email: min.tsai@pymetrics.com
Requires-Python: >=3.6,<4.0
Classifier: License :: OSI Approved :: MIT License
Classifier: Programming Language :: Python :: 3
Classifier: Programming Language :: Python :: 3.6
Classifier: Programming Language :: Python :: 3.7
Classifier: Programming Language :: Python :: 3.8
Classifier: Programming Language :: Python :: 3.9
Requires-Dist: attrs (>=20.1.0,<22.0.0)
Requires-Dist: httpx (>=0.15.4,<0.21.0)
Requires-Dist: python-dateutil (>=2.8.0,<3.0.0)
Project-URL: Repository, https://github.com/pymetrics/pymetrics_assessment_api_client
